{
  "$schema": "https://developer.microsoft.com/json-schemas/fabric/item/report/definition/visualContainer/2.8.0/schema.json",
  "name": "kpi_28d_ma",
  "position": {
    "x": 732,
    "y": 100,
    "z": 0,
    "height": 120,
    "width": 220,
    "tabOrder": 5
  },
  "visual": {
    "visualType": "card",
    "query": {
      "queryState": {
        "Values": {
          "projections": [
            {
              "field": {
                "Measure": {
                  "Expression": {
                    "SourceRef": {
                      "Entity": "_Measures"
                    }
                  },
                  "Property": "28-Day MA Revenue"
                }
              },
              "queryRef": "_Measures.28-Day MA Revenue",
              "nativeQueryRef": "28-Day Trend"
            }
          ]
        }
      }
    },
    "visualContainerObjects": {
      "title": [
        {
          "properties": {
            "show": {
              "expr": {
                "Literal": {
                  "Value": "true"
                }
              }
            },
            "text": {
              "expr": {
                "Literal": {
                  "Value": "'28-Day Trend'"
                }
              }
            }
          }
        }
      ]
    },
    "drillFilterOtherVisuals": true
  }
}