{
  "$schema": "https://developer.microsoft.com/json-schemas/fabric/item/report/definition/visualContainer/2.8.0/schema.json",
  "name": "8b716a568143c3e04711",
  "position": {
    "x": 1613.9327892949466,
    "y": 86.418977140250391,
    "z": 11001,
    "height": 93.425921232703132,
    "width": 266.26387551320391,
    "tabOrder": 11001
  },
  "visual": {
    "visualType": "slicer",
    "query": {
      "queryState": {
        "Values": {
          "projections": [
            {
              "field": {
                "Column": {
                  "Expression": {
                    "SourceRef": {
                      "Entity": "DIM_DATES"
                    }
                  },
                  "Property": "YEAR"
                }
              },
              "queryRef": "DIM_DATES.YEAR",
              "nativeQueryRef": "YEAR",
              "active": true
            }
          ]
        }
      }
    },
    "objects": {
      "data": [
        {
          "properties": {
            "mode": {
              "expr": {
                "Literal": {
                  "Value": "'Between'"
                }
              }
            }
          }
        }
      ],
      "general": [
        {
          "properties": {}
        }
      ]
    },
    "visualContainerObjects": {
      "title": [
        {
          "properties": {
            "show": {
              "expr": {
                "Literal": {
                  "Value": "false"
                }
              }
            }
          }
        }
      ],
      "dropShadow": [
        {
          "properties": {
            "shadowDistance": {
              "expr": {
                "Literal": {
                  "Value": "1D"
                }
              }
            },
            "shadowSpread": {
              "expr": {
                "Literal": {
                  "Value": "1D"
                }
              }
            },
            "color": {
              "solid": {
                "color": {
                  "expr": {
                    "Literal": {
                      "Value": "'#E0E0E0'"
                    }
                  }
                }
              }
            }
          }
        }
      ]
    },
    "drillFilterOtherVisuals": true
  }
}